{
	"info": {
		"_postman_id": "6c9e212b-7a3c-43ba-adbe-762bc14c4ec3",
		"name": "DAI_TP4",
		"schema": "https://schema.getpostman.com/json/collection/v2.1.0/collection.json"
	},
	"item": [
		{
			"name": "http://localhost:3000/api/province/1 Copy 2",
			"protocolProfileBehavior": {
				"disableBodyPruning": true
			},
			"request": {
				"method": "GET",
				"header": [],
				"body": {
					"mode": "raw",
					"raw": "",
					"options": {
						"raw": {
							"language": "json"
						}
					}
				},
				"url": {
					"raw": "http://localhost:3000/api/province/",
					"protocol": "http",
					"host": [
						"localhost"
					],
					"port": "3000",
					"path": [
						"api",
						"province",
						""
					]
				}
			},
			"response": []
		},
		{
			"name": "http://localhost:3000/api/province/1 Copy",
			"protocolProfileBehavior": {
				"disableBodyPruning": true
			},
			"request": {
				"method": "GET",
				"header": [],
				"body": {
					"mode": "raw",
					"raw": "",
					"options": {
						"raw": {
							"language": "json"
						}
					}
				},
				"url": {
					"raw": "http://localhost:3000/api/province/2",
					"protocol": "http",
					"host": [
						"localhost"
					],
					"port": "3000",
					"path": [
						"api",
						"province",
						"2"
					]
				}
			},
			"response": []
		},
		{
			"name": "http://localhost:3000/api/province/1 Copy 3",
			"request": {
				"method": "POST",
				"header": [],
				"body": {
					"mode": "raw",
					"raw": "{\r\n    \"name\":\"Lishii\",\r\n    \"full_name\":\"Vireinado de Lifschitz\",\r\n    \"latitude\":\"-69.213456789213451\",\r\n    \"longitude\":\"42.61446691796875\",\r\n    \"display_order\":null\r\n}",
					"options": {
						"raw": {
							"language": "json"
						}
					}
				},
				"url": {
					"raw": "http://localhost:3000/api/province/",
					"protocol": "http",
					"host": [
						"localhost"
					],
					"port": "3000",
					"path": [
						"api",
						"province",
						""
					]
				}
			},
			"response": []
		},
		{
			"name": "http://localhost:3000/api/province/1 Copy 4",
			"request": {
				"method": "PUT",
				"header": [],
				"body": {
					"mode": "raw",
					"raw": "{\r\n    \"name\":\"Lishii\",\r\n    \"full_name\":\"Vireinado de Lifschitz\",\r\n    \"latitude\":\"-69.213456789213451\",\r\n    \"longitude\":\"42.61446691796875\",\r\n    \"display_order\":null,\r\n    \"id\":1\r\n}",
					"options": {
						"raw": {
							"language": "json"
						}
					}
				},
				"url": {
					"raw": "http://localhost:3000/api/province/",
					"protocol": "http",
					"host": [
						"localhost"
					],
					"port": "3000",
					"path": [
						"api",
						"province",
						""
					]
				}
			},
			"response": []
		},
		{
			"name": "http://localhost:3000/api/province/1",
			"request": {
				"method": "DELETE",
				"header": [],
				"body": {
					"mode": "raw",
					"raw": "",
					"options": {
						"raw": {
							"language": "json"
						}
					}
				},
				"url": {
					"raw": "http://localhost:3000/api/province/1",
					"protocol": "http",
					"host": [
						"localhost"
					],
					"port": "3000",
					"path": [
						"api",
						"province",
						"1"
					]
				}
			},
			"response": []
		}
	]
}